drf_easyview/__init__.py
drf_easyview/apps.py
drf_easyview/serializers.py
drf_easyview/urls.py
drf_easyview/utils.py
drf_easyview/views.py
drf_easyview-2.0.2.dist-info/LICENSE
drf_easyview-2.0.2.dist-info/METADATA
drf_easyview-2.0.2.dist-info/WHEEL
drf_easyview-2.0.2.dist-info/top_level.txt
drf_easyview-2.0.2.dist-info/RECORD
